sai_env/__init__.py
sai_env/utils/__init__.py
sai_env/utils/utils.py
sai_env-0.0.1.dist-info/METADATA
sai_env-0.0.1.dist-info/WHEEL
sai_env-0.0.1.dist-info/licenses/LICENSE
sai_env-0.0.1.dist-info/RECORD
