Metadata-Version: 2.4
Name: sai_env
Version: 0.0.1
Summary: A collection of utility files for the SAI platform.
Author-email: ArenaX Labs <research@competesai.com>
License: MIT
License-File: LICENSE
Requires-Python: >=3.10
Requires-Dist: gymnasium>=1.0.0
Requires-Dist: numpy==1.26.0
Requires-Dist: pydantic
Requires-Dist: pyyaml
